fraposa_pgsc/__init__.py
fraposa_pgsc/fraposa.py
fraposa_pgsc/fraposa_runner.py
fraposa_pgsc/plotpcs.py
fraposa_pgsc/predstupopu.py
fraposa_pgsc/variants.py
fraposa_pgsc-1.0.2.dist-info/LICENSE
fraposa_pgsc-1.0.2.dist-info/METADATA
fraposa_pgsc-1.0.2.dist-info/WHEEL
fraposa_pgsc-1.0.2.dist-info/entry_points.txt
fraposa_pgsc-1.0.2.dist-info/RECORD
