Metadata-Version: 2.1
Name: fraposa-pgsc
Version: 1.0.2
Summary: Tools to perform ancestry projection to a reference dataset within the calculator pipeline (pgsc_calc)
Home-page: https://github.com/PGScatalog/fraposa_pgsc
License: MIT
Author: smlmbrt
Author-email: sam.a.lambert@gmail.com
Requires-Python: >=3.10,<4.0
Classifier: License :: OSI Approved :: MIT License
Classifier: Programming Language :: Python :: 3
Classifier: Programming Language :: Python :: 3.10
Classifier: Programming Language :: Python :: 3.11
Classifier: Programming Language :: Python :: 3.12
Requires-Dist: matplotlib (>=3.7.1,<4.0.0)
Requires-Dist: numpy (>=1.24.2,<2.0.0)
Requires-Dist: pandas (>=1.5.3,<2.0.0)
Requires-Dist: pyplink (>=1.3.5,<2.0.0)
Requires-Dist: scikit-learn (>=1.2.1,<2.0.0)
